maskz/__init__.py
maskz/ai.py
maskz/bool.py
maskz/boolo.py
maskz/files.py
maskz/math.py
maskz/module.py
maskz/websear.py
maskz/pr/__init__.py
maskz/pr/bool.py
maskz/pr/boolo.py
maskz/pr/diff.py
MaskZ-1.2.1.dist-info/METADATA
MaskZ-1.2.1.dist-info/WHEEL
MaskZ-1.2.1.dist-info/top_level.txt
MaskZ-1.2.1.dist-info/RECORD
