Metadata-Version: 2.1
Name: MaskZ
Version: 1.2.1
Summary: MaskZ, a package intended to make all of the python users life easier 
Home-page: UNKNOWN
Author: Saad-py
Author-email: saadyarkhan11@gmail.com
License: UNKNOWN
Platform: UNKNOWN
Requires-Dist: pyttsx3
Requires-Dist: playsound
Requires-Dist: pywin32
Requires-Dist: gtts
Requires-Dist: kivy
Requires-Dist: importlib
Requires-Dist: pandas
Requires-Dist: pathlib
